Lab4_Verilog_Conductual/div3_tester.v
module div3_tester (
    output reg A,
    output reg B,
    output reg C,
    output reg D,
    input Y
);
    initial begin
        $dumpfile("simulacion_div3.vcd");
        $dumpvars();
        {A,B,C,D} = 0; #10
        {A,B,C,D} = 1; #10
        {A,B,C,D} = 2; #10
        {A,B,C,D} = 3; #10
        {A,B,C,D} = 4; #10
        {A,B,C,D} = 5; #10
        {A,B,C,D} = 6; #10
        {A,B,C,D} = 7; #10
        {A,B,C,D} = 8; #10
        {A,B,C,D} = 9; #10
        {A,B,C,D} = 10; #10
        {A,B,C,D} = 11; #10
        {A,B,C,D} = 12; #10
        {A,B,C,D} = 13; #10
        {A,B,C,D} = 14; #10
        {A,B,C,D} = 15; #10
        $finish;
    end
endmodule

Lab4_Verilog_Conductual/div3.v
//Declaración del módulo
module div3 (
    //Interfaz del módulo
    input A,
    input B,
    input C,
    input D,
    output Y
);
    //Declaración de señales intermedias
    wire notA, notB, notD;
    wire notA_and_notB, C_xnor_D, term_1;
    wire B_and_notD, A_xor_C, term_2;
    wire A_and_D, B_xnor_C, term_3;

    //Entradas Invertidas
    not G1 (notA, A);
    not G2 (notB, B);
    not G3 (notD, D);

    //Primer Término
    and  G4 (notA_and_notB, notA, notB);
    xnor G5 (C_xnor_D, C, D);
    and  G6 (term_1, notA_and_notB, C_xnor_D);

    //Segundo Término
    and G7 (B_and_notD, B, notD);
    xor G8 (A_xor_C, A, C);
    and G9 (term_2, B_and_notD, A_xor_C);

    //Tercer Término
    and  G10 (A_and_D, A, D);
    xnor G11 (B_xnor_C, B, C);
    and  G12 (term_3, A_and_D, B_xnor_C);

    //OR de los tres
    or G13 (Y, term_1, term_2, term_3);

endmodule

Lab4_Verilog_Conductual/div3_tb.v
`include "div3.v"
`include "div3_tester.v"

module div3_tb;
    //Cables que se utilizarán para interconectar los módulos
    wire A, B, C, D, Y;

    //Instancia del módulo bajo prueba
    //Este tipo de instanciación se llama "por nombre"
    //En este caso los nombres de los wires en el tb 
    //y los puertos en el dut coinciden, pero no es necesario
    //que eso ocurra
    div3 dut (
        .A(A),
        .B(B),
        .C(C),
        .D(D),
        .Y(Y)
    );

    //Instaciación del tester
    //Este tipo de instanciación se llama "por orden"
    //Las señales se deben pasar en el mismo orden en el que
    //fueron declaradas en el módulo
    //Esta forma es más compacta, pero la otra es más legible
    div3_tester tester (A, B, C, D, Y);
    
endmodule

Lab4_Verilog_Conductual/simulacion_div3.vcd
$date
	Tue Jul 22 08:52:47 2025
$end
$version
	Icarus Verilog
$end
$timescale
	1s
$end
$scope module div3_tb $end
$var wire 1 ! Y $end
$var wire 1 " D $end
$var wire 1 # C $end
$var wire 1 $ B $end
$var wire 1 % A $end
$scope module dut $end
$var wire 1 & A_and_D $end
$var wire 1 ' A_xor_C $end
$var wire 1 ( B_and_notD $end
$var wire 1 ) B_xnor_C $end
$var wire 1 * C_xnor_D $end
$var wire 1 ! Y $end
$var wire 1 + notA $end
$var wire 1 , notA_and_notB $end
$var wire 1 - notB $end
$var wire 1 . notD $end
$var wire 1 / term_1 $end
$var wire 1 0 term_2 $end
$var wire 1 1 term_3 $end
$var wire 1 " D $end
$var wire 1 # C $end
$var wire 1 $ B $end
$var wire 1 % A $end
$upscope $end
$scope module tester $end
$var wire 1 ! Y $end
$var reg 1 % A $end
$var reg 1 $ B $end
$var reg 1 # C $end
$var reg 1 " D $end
$upscope $end
$upscope $end
$enddefinitions $end
#0
$dumpvars
01
00
1/
1.
1-
1,
1+
1*
1)
0(
0'
0&
0%
0$
0#
0"
1!
$end
#10
0!
0/
0*
0.
1"
#20
0)
1'
1.
1#
0"
#30
1!
1/
1*
0.
1"
#40
0!
0/
0,
1(
0-
0'
1.
1$
0#
0"
#50
0(
0*
0.
1"
#60
1!
10
1(
1)
1'
1.
1#
0"
#70
0!
00
0(
1*
0.
1"
#80
0+
1-
1.
1%
0$
0#
0"
#90
1!
11
1&
0*
0.
1"
#100
0!
01
0)
0'
0&
1.
1#
0"
#110
1&
1*
0.
1"
#120
1!
10
1(
0-
1'
0&
1.
1$
0#
0"
#130
0!
00
0(
1&
0*
0.
1"
#140
1(
1)
0'
0&
1.
1#
0"
#150
1!
11
0(
1&
1*
0.
1"
